loop_win.py
term_fix.py
mcol/__init__.py
mcol/colours.py
mgo/__init__.py
mgo/io.py
mgo/primitives.py
mlog/__init__.py
mlog/logs.py
mlog/test_log.py
mout/__init__.py
mout/ase.py
mout/convert.py
mout/deco.py
mout/fileio.py
mout/output.py
mout/print.py
mout/progress.py
mout/testing.py
mplot/__init__.py
mplot/fit.py
mplot/graph2D.py
mplot/hist1D.py
mplot/hist2D.py
mplot/main.py
mplot/surf3D.py
mrich/__init__.py
mrich/colors.py
mrich/console.py
mrich/df.py
mrich/functions.py
mrich/patch.py
mrich/spinners.py
mrich/tools.py
mrich/wrappers.py
mwin/__init__.py
mwin/curses.py
mwin/window.py
mpytools-0.0.28.dist-info/METADATA
mpytools-0.0.28.dist-info/WHEEL
mpytools-0.0.28.dist-info/RECORD
