Metadata-Version: 2.4
Name: MPyTools
Version: 0.0.28
Summary: Convenient tools for CLI, GUI, and plotting
Project-URL: Homepage, https://github.com/mwinokan/MPyTools
Project-URL: Bug Tracker, https://github.com/mwinokan/MPyTools/issues
Author-email: Max Winokan <max@winokan.com>
Classifier: License :: OSI Approved :: MIT License
Classifier: Operating System :: OS Independent
Classifier: Programming Language :: Python :: 3
Requires-Python: >=3.9
Requires-Dist: cycler
Requires-Dist: emoji
Requires-Dist: haggis
Requires-Dist: matplotlib
Requires-Dist: numpy
Requires-Dist: plotly
Requires-Dist: rich
